py_executable_checklist/__init__.py
py_executable_checklist/py.typed
py_executable_checklist/workflow.py
py_executable_checklist-1.4.0.dist-info/METADATA
py_executable_checklist-1.4.0.dist-info/WHEEL
py_executable_checklist-1.4.0.dist-info/RECORD
