Metadata-Version: 2.1
Name: py-executable-checklist
Version: 1.4.0
Summary: Helper classes to develop executable workflow scripts
Home-page: https://namuan.github.io/py-executable-checklist
License: MIT
Author: namuan
Author-email: github@deskriders.dev
Requires-Python: >=3.7.1,<4.0
Classifier: Development Status :: 4 - Beta
Classifier: Intended Audience :: Developers
Classifier: License :: OSI Approved :: MIT License
Classifier: Operating System :: OS Independent
Classifier: Programming Language :: Python
Classifier: Programming Language :: Python :: 3
Classifier: Programming Language :: Python :: 3.8
Classifier: Programming Language :: Python :: 3.9
Classifier: Programming Language :: Python :: 3.10
Classifier: Programming Language :: Python :: 3.11
Classifier: Programming Language :: Python :: 3
Classifier: Programming Language :: Python :: 3.7
Classifier: Programming Language :: Python :: 3.8
Classifier: Programming Language :: Python :: 3.9
Classifier: Topic :: Software Development :: Libraries :: Python Modules
Classifier: Typing :: Typed
Project-URL: Documentation, https://namuan.github.io/py-executable-checklist
Project-URL: Repository, https://github.com/namuan/py-executable-checklist
